<?xml version="1.0" encoding="UTF-8" standalone="no"?>
<!DOCTYPE log SYSTEM "logger.dtd">
<log>
<record>
  <date>2022-12-09T18:18:05</date>
  <millis>1670590085883</millis>
  <sequence>0</sequence>
  <logger>scpLog</logger>
  <level>CONFIG</level>
  <class>com.sgs.sos.common.CryptoManager</class>
  <method>init</method>
  <thread>1</thread>
  <message>crypto Key generated</message>
</record>
<record>
  <date>2022-12-09T18:18:05</date>
  <millis>1670590085978</millis>
  <sequence>1</sequence>
  <logger>scpLog</logger>
  <level>CONFIG</level>
  <class>com.sgs.sos.server.ServerMain$ServerThread</class>
  <method>run</method>
  <thread>11</thread>
  <message>Web+Scp : Server Started listening on port 8080</message>
</record>
<record>
  <date>2022-12-09T18:18:05</date>
  <millis>1670590085979</millis>
  <sequence>2</sequence>
  <logger>scpLog</logger>
  <level>CONFIG</level>
  <class>com.sgs.sos.server.ServerMain$ServerThread</class>
  <method>run</method>
  <thread>11</thread>
  <message>------------------------- SERVER STARTED SUCCESSFULLY -------------------------------</message>
</record>
<record>
  <date>2022-12-09T18:18:05</date>
  <millis>1670590085982</millis>
  <sequence>3</sequence>
  <logger>scpLog</logger>
  <level>CONFIG</level>
  <class>com.sgs.sos.server.ScpSocketHandler$DownstreamResponder</class>
  <method>init</method>
  <thread>1</thread>
  <message>Scp-ds: D/S responder open at port : 8086</message>
</record>
<record>
  <date>2022-12-09T18:18:05</date>
  <millis>1670590085982</millis>
  <sequence>4</sequence>
  <logger>scpLog</logger>
  <level>CONFIG</level>
  <class>com.sgs.sos.server.ScpSocketHandler$UpstreamListener</class>
  <method>run</method>
  <thread>12</thread>
  <message>Scp Listener started at port :8085</message>
</record>
<record>
  <date>2022-12-09T18:18:05</date>
  <millis>1670590085984</millis>
  <sequence>5</sequence>
  <logger>scpLog</logger>
  <level>WARNING</level>
  <class>com.sgs.sos.test.TestMain</class>
  <method>test</method>
  <thread>1</thread>
  <message>Current Local IP address : 192.168.59.229</message>
</record>
<record>
  <date>2022-12-09T18:18:06</date>
  <millis>1670590086017</millis>
  <sequence>6</sequence>
  <logger>scpLog</logger>
  <level>INFO</level>
  <class>com.sgs.sos.test.TestMain</class>
  <method>testPDU</method>
  <thread>1</thread>
  <message>PREP ScpData{header=ScpHeader{reserved=3, destAddress=[-64, -88, 59, -27], srcAddress=[-64, -88, 59, -27], payloadLength=0, timestamp=1670590085989, ssid=-9169946474402462823, padding=0, priorityMode=17, HMAC=-75241946, scpUnitCount=0, header=[3, 17, 0, 0, -5, -125, -26, 38, -64, -88, 59, -27, -64, -88, 59, -27, 0, 0, 1, -124, -10, -19, -69, 101, -128, -67, -50, 68, 23, -27, 67, -103], pdu=true}, messageUnits=[], scpData=[3, 17, 0, 0, -5, -125, -26, 38, -64, -88, 59, -27, -64, -88, 59, -27, 0, 0, 1, -124, -10, -19, -69, 101, -128, -67, -50, 68, 23, -27, 67, -103, 80, 0, 0, 0, -94, 48, -127, -97, 48, 13, 6, 9, 42, -122, 72, -122, -9, 13, 1, 1, 1, 5, 0, 3, -127, -115, 0, 48, -127, -119, 2, -127, -127, 0, -85, -9, -71, -106, -118, -99, -30, 45, -68, -69, 45, 118, 32, -108, 93, -38, -128, 7, 41, -31, -89, 98, -75, 15, -18, -22, -35, -89, 28, -121, -82, 46, -21, 39, -55, -30, -57, 116, 21, 96, -74, 67, 82, 17, 100, -71, -115, -34, -9, -84, 100, -94, -42, 89, 85, -122, -100, 1, 85, -40, 127, 56, -103, -69, -56, -96, 71, -67, -4, -75, -31, 41, 7, 30, 44, -87, -8, -26, -119, 34, 26, -98, -116, -43, -12, 32, -59, -73, -75, -79, 13, 6, -48, -26, -16, 126, 50, 127, 18, -53, -101, -9, -99, 6, 53, 121, -67, -35, 49, -7, -110, -118, -118, -76, -39, 22, 18, -53, 72, -114, -121, -63, -83, 41, -29, -28, 110, 97, 2, 3, 1, 0, 1], payload=[80, 0, 0, 0, -94, 48, -127, -97, 48, 13, 6, 9, 42, -122, 72, -122, -9, 13, 1, 1, 1, 5, 0, 3, -127, -115, 0, 48, -127, -119, 2, -127, -127, 0, -85, -9, -71, -106, -118, -99, -30, 45, -68, -69, 45, 118, 32, -108, 93, -38, -128, 7, 41, -31, -89, 98, -75, 15, -18, -22, -35, -89, 28, -121, -82, 46, -21, 39, -55, -30, -57, 116, 21, 96, -74, 67, 82, 17, 100, -71, -115, -34, -9, -84, 100, -94, -42, 89, 85, -122, -100, 1, 85, -40, 127, 56, -103, -69, -56, -96, 71, -67, -4, -75, -31, 41, 7, 30, 44, -87, -8, -26, -119, 34, 26, -98, -116, -43, -12, 32, -59, -73, -75, -79, 13, 6, -48, -26, -16, 126, 50, 127, 18, -53, -101, -9, -99, 6, 53, 121, -67, -35, 49, -7, -110, -118, -118, -76, -39, 22, 18, -53, 72, -114, -121, -63, -83, 41, -29, -28, 110, 97, 2, 3, 1, 0, 1], pdu=ScpDataUnit{payload=[48, -127, -97, 48, 13, 6, 9, 42, -122, 72, -122, -9, 13, 1, 1, 1, 5, 0, 3, -127, -115, 0, 48, -127, -119, 2, -127, -127, 0, -85, -9, -71, -106, -118, -99, -30, 45, -68, -69, 45, 118, 32, -108, 93, -38, -128, 7, 41, -31, -89, 98, -75, 15, -18, -22, -35, -89, 28, -121, -82, 46, -21, 39, -55, -30, -57, 116, 21, 96, -74, 67, 82, 17, 100, -71, -115, -34, -9, -84, 100, -94, -42, 89, 85, -122, -100, 1, 85, -40, 127, 56, -103, -69, -56, -96, 71, -67, -4, -75, -31, 41, 7, 30, 44, -87, -8, -26, -119, 34, 26, -98, -116, -43, -12, 32, -59, -73, -75, -79, 13, 6, -48, -26, -16, 126, 50, 127, 18, -53, -101, -9, -99, 6, 53, 121, -67, -35, 49, -7, -110, -118, -118, -76, -39, 22, 18, -53, 72, -114, -121, -63, -83, 41, -29, -28, 110, 97, 2, 3, 1, 0, 1], pduType=80, payloadLength=162}}</message>
</record>
<record>
  <date>2022-12-09T18:18:06</date>
  <millis>1670590086019</millis>
  <sequence>7</sequence>
  <logger>scpLog</logger>
  <level>INFO</level>
  <class>com.sgs.sos.test.TestMain</class>
  <method>testPDU</method>
  <thread>1</thread>
  <message>PREP [80, 0, 0, 0, -94, 48, -127, -97, 48, 13, 6, 9, 42, -122, 72, -122, -9, 13, 1, 1, 1, 5, 0, 3, -127, -115, 0, 48, -127, -119, 2, -127, -127, 0, -85, -9, -71, -106, -118, -99, -30, 45, -68, -69, 45, 118, 32, -108, 93, -38, -128, 7, 41, -31, -89, 98, -75, 15, -18, -22, -35, -89, 28, -121, -82, 46, -21, 39, -55, -30, -57, 116, 21, 96, -74, 67, 82, 17, 100, -71, -115, -34, -9, -84, 100, -94, -42, 89, 85, -122, -100, 1, 85, -40, 127, 56, -103, -69, -56, -96, 71, -67, -4, -75, -31, 41, 7, 30, 44, -87, -8, -26, -119, 34, 26, -98, -116, -43, -12, 32, -59, -73, -75, -79, 13, 6, -48, -26, -16, 126, 50, 127, 18, -53, -101, -9, -99, 6, 53, 121, -67, -35, 49, -7, -110, -118, -118, -76, -39, 22, 18, -53, 72, -114, -121, -63, -83, 41, -29, -28, 110, 97, 2, 3, 1, 0, 1]</message>
</record>
<record>
  <date>2022-12-09T18:18:06</date>
  <millis>1670590086022</millis>
  <sequence>8</sequence>
  <logger>scpLog</logger>
  <level>INFO</level>
  <class>com.sgs.sos.io.ScpInputHandler</class>
  <method>handle</method>
  <thread>12</thread>
  <message>REQUEST_IN -&gt; address_in=192.168.59.229:8086</message>
</record>
<record>
  <date>2022-12-09T18:18:06</date>
  <millis>1670590086024</millis>
  <sequence>9</sequence>
  <logger>scpLog</logger>
  <level>INFO</level>
  <class>com.sgs.sos.io.ScpInputHandler</class>
  <method>handle</method>
  <thread>12</thread>
  <message>ScpData{header=ScpHeader{reserved=3, destAddress=[-64, -88, 59, -27], srcAddress=[-64, -88, 59, -27], payloadLength=0, timestamp=1670590085989, ssid=-9169946474402462823, padding=0, priorityMode=17, HMAC=-75241946, scpUnitCount=0, header=[3, 17, 0, 0, -5, -125, -26, 38, -64, -88, 59, -27, -64, -88, 59, -27, 0, 0, 1, -124, -10, -19, -69, 101, -128, -67, -50, 68, 23, -27, 67, -103], pdu=true}, messageUnits=null, scpData=[3, 17, 0, 0, -5, -125, -26, 38, -64, -88, 59, -27, -64, -88, 59, -27, 0, 0, 1, -124, -10, -19, -69, 101, -128, -67, -50, 68, 23, -27, 67, -103, 80, 0, 0, 0, -94, 48, -127, -97, 48, 13, 6, 9, 42, -122, 72, -122, -9, 13, 1, 1, 1, 5, 0, 3, -127, -115, 0, 48, -127, -119, 2, -127, -127, 0, -85, -9, -71, -106, -118, -99, -30, 45, -68, -69, 45, 118, 32, -108, 93, -38, -128, 7, 41, -31, -89, 98, -75, 15, -18, -22, -35, -89, 28, -121, -82, 46, -21, 39, -55, -30, -57, 116, 21, 96, -74, 67, 82, 17, 100, -71, -115, -34, -9, -84, 100, -94, -42, 89, 85, -122, -100, 1, 85, -40, 127, 56, -103, -69, -56, -96, 71, -67, -4, -75, -31, 41, 7, 30, 44, -87, -8, -26, -119, 34, 26, -98, -116, -43, -12, 32, -59, -73, -75, -79, 13, 6, -48, -26, -16, 126, 50, 127, 18, -53, -101, -9, -99, 6, 53, 121, -67, -35, 49, -7, -110, -118, -118, -76, -39, 22, 18, -53, 72, -114, -121, -63, -83, 41, -29, -28, 110, 97, 2, 3, 1, 0, 1], payload=[80, 0, 0, 0, -94, 48, -127, -97, 48, 13, 6, 9, 42, -122, 72, -122, -9, 13, 1, 1, 1, 5, 0, 3, -127, -115, 0, 48, -127, -119, 2, -127, -127, 0, -85, -9, -71, -106, -118, -99, -30, 45, -68, -69, 45, 118, 32, -108, 93, -38, -128, 7, 41, -31, -89, 98, -75, 15, -18, -22, -35, -89, 28, -121, -82, 46, -21, 39, -55, -30, -57, 116, 21, 96, -74, 67, 82, 17, 100, -71, -115, -34, -9, -84, 100, -94, -42, 89, 85, -122, -100, 1, 85, -40, 127, 56, -103, -69, -56, -96, 71, -67, -4, -75, -31, 41, 7, 30, 44, -87, -8, -26, -119, 34, 26, -98, -116, -43, -12, 32, -59, -73, -75, -79, 13, 6, -48, -26, -16, 126, 50, 127, 18, -53, -101, -9, -99, 6, 53, 121, -67, -35, 49, -7, -110, -118, -118, -76, -39, 22, 18, -53, 72, -114, -121, -63, -83, 41, -29, -28, 110, 97, 2, 3, 1, 0, 1], pdu=ScpDataUnit{payload=[48, -127, -97, 48, 13, 6, 9, 42, -122, 72, -122, -9, 13, 1, 1, 1, 5, 0, 3, -127, -115, 0, 48, -127, -119, 2, -127, -127, 0, -85, -9, -71, -106, -118, -99, -30, 45, -68, -69, 45, 118, 32, -108, 93, -38, -128, 7, 41, -31, -89, 98, -75, 15, -18, -22, -35, -89, 28, -121, -82, 46, -21, 39, -55, -30, -57, 116, 21, 96, -74, 67, 82, 17, 100, -71, -115, -34, -9, -84, 100, -94, -42, 89, 85, -122, -100, 1, 85, -40, 127, 56, -103, -69, -56, -96, 71, -67, -4, -75, -31, 41, 7, 30, 44, -87, -8, -26, -119, 34, 26, -98, -116, -43, -12, 32, -59, -73, -75, -79, 13, 6, -48, -26, -16, 126, 50, 127, 18, -53, -101, -9, -99, 6, 53, 121, -67, -35, 49, -7, -110, -118, -118, -76, -39, 22, 18, -53, 72, -114, -121, -63, -83, 41, -29, -28, 110, 97, 2, 3, 1, 0, 1], pduType=80, payloadLength=162}}</message>
</record>
<record>
  <date>2022-12-09T18:18:06</date>
  <millis>1670590086026</millis>
  <sequence>10</sequence>
  <logger>scpLog</logger>
  <level>INFO</level>
  <class>com.sgs.sos.server.ScpSocketHandler$DownstreamResponder</class>
  <method>sendResponse</method>
  <thread>1</thread>
  <message>DATA_OUT -&gt; destination=192.168.59.229:8085</message>
</record>
<record>
  <date>2022-12-09T18:18:06</date>
  <millis>1670590086027</millis>
  <sequence>11</sequence>
  <logger>scpLog</logger>
  <level>INFO</level>
  <class>com.sgs.sos.io.ScpProcessor</class>
  <method>process</method>
  <thread>12</thread>
  <message>Processing ScpData =&gt; ssid=-9169946474402462823</message>
</record>
<record>
  <date>2022-12-09T18:18:11</date>
  <millis>1670590091031</millis>
  <sequence>12</sequence>
  <logger>scpLog</logger>
  <level>INFO</level>
  <class>com.sgs.sos.test.TestMain</class>
  <method>testPMU</method>
  <thread>1</thread>
  <message>PREP ScpData{header=ScpHeader{reserved=3, destAddress=[-64, -88, 59, -27], srcAddress=[-64, -88, 59, -27], payloadLength=11, timestamp=1670590091028, ssid=-6524828381272499927, padding=0, priorityMode=1, HMAC=1426084048, scpUnitCount=2, header=[3, 1, 11, 2, 85, 0, 80, -48, -64, -88, 59, -27, -64, -88, 59, -27, 0, 0, 1, -124, -10, -19, -49, 20, -91, 115, 39, 40, 65, -35, -103, 41], pdu=false}, messageUnits=[ScpMessageUnit{message=[84, 101, 115, 116], length=4, type=1}, ScpMessageUnit{message=[66, 89, 69], length=3, type=0}], scpData=[3, 1, 11, 2, 85, 0, 80, -48, -64, -88, 59, -27, -64, -88, 59, -27, 0, 0, 1, -124, -10, -19, -49, 20, -91, 115, 39, 40, 65, -35, -103, 41, 1, 4, 84, 101, 115, 116, 0, 3, 66, 89, 69], payload=[1, 4, 84, 101, 115, 116, 0, 3, 66, 89, 69], pdu=null}</message>
</record>
<record>
  <date>2022-12-09T18:18:11</date>
  <millis>1670590091033</millis>
  <sequence>13</sequence>
  <logger>scpLog</logger>
  <level>INFO</level>
  <class>com.sgs.sos.test.TestMain</class>
  <method>testPMU</method>
  <thread>1</thread>
  <message>PREP [1, 4, 84, 101, 115, 116, 0, 3, 66, 89, 69]</message>
</record>
<record>
  <date>2022-12-09T18:18:11</date>
  <millis>1670590091035</millis>
  <sequence>14</sequence>
  <logger>scpLog</logger>
  <level>INFO</level>
  <class>com.sgs.sos.server.ScpSocketHandler$DownstreamResponder</class>
  <method>sendResponse</method>
  <thread>1</thread>
  <message>DATA_OUT -&gt; destination=192.168.59.229:8085</message>
</record>
<record>
  <date>2022-12-09T18:18:11</date>
  <millis>1670590091035</millis>
  <sequence>15</sequence>
  <logger>scpLog</logger>
  <level>INFO</level>
  <class>com.sgs.sos.io.ScpInputHandler</class>
  <method>handle</method>
  <thread>12</thread>
  <message>REQUEST_IN -&gt; address_in=192.168.59.229:8086</message>
</record>
<record>
  <date>2022-12-09T18:18:11</date>
  <millis>1670590091037</millis>
  <sequence>16</sequence>
  <logger>scpLog</logger>
  <level>INFO</level>
  <class>com.sgs.sos.io.ScpInputHandler</class>
  <method>handle</method>
  <thread>12</thread>
  <message>ScpData{header=ScpHeader{reserved=3, destAddress=[-64, -88, 59, -27], srcAddress=[-64, -88, 59, -27], payloadLength=11, timestamp=1670590091028, ssid=-6524828381272499927, padding=0, priorityMode=1, HMAC=1426084048, scpUnitCount=2, header=[3, 1, 11, 2, 85, 0, 80, -48, -64, -88, 59, -27, -64, -88, 59, -27, 0, 0, 1, -124, -10, -19, -49, 20, -91, 115, 39, 40, 65, -35, -103, 41], pdu=false}, messageUnits=[ScpMessageUnit{message=[84, 101, 115, 116], length=4, type=1}, ScpMessageUnit{message=[66, 89, 69], length=3, type=0}], scpData=[3, 1, 11, 2, 85, 0, 80, -48, -64, -88, 59, -27, -64, -88, 59, -27, 0, 0, 1, -124, -10, -19, -49, 20, -91, 115, 39, 40, 65, -35, -103, 41, 1, 4, 84, 101, 115, 116, 0, 3, 66, 89, 69], payload=[1, 4, 84, 101, 115, 116, 0, 3, 66, 89, 69], pdu=null}</message>
</record>
<record>
  <date>2022-12-09T18:18:11</date>
  <millis>1670590091038</millis>
  <sequence>17</sequence>
  <logger>scpLog</logger>
  <level>INFO</level>
  <class>com.sgs.sos.io.ScpProcessor</class>
  <method>process</method>
  <thread>12</thread>
  <message>Processing ScpData =&gt; ssid=-6524828381272499927</message>
</record>
<record>
  <date>2022-12-09T18:18:50</date>
  <millis>1670590130475</millis>
  <sequence>18</sequence>
  <logger>scpLog</logger>
  <level>INFO</level>
  <class>com.sgs.sos.server.HttpResourceServerThread</class>
  <method>run</method>
  <thread>15</thread>
  <message> Web Req received :/test</message>
</record>
<record>
  <date>2022-12-09T18:18:50</date>
  <millis>1670590130476</millis>
  <sequence>19</sequence>
  <logger>scpLog</logger>
  <level>INFO</level>
  <class>com.sgs.sos.test.TestMain</class>
  <method>testHTTPWithPDU</method>
  <thread>15</thread>
  <message>PREP ScpData{header=ScpHeader{reserved=3, destAddress=[-64, -88, 59, -27], srcAddress=[-64, -88, 59, -27], payloadLength=0, timestamp=1670590130476, ssid=4169821602055209071, padding=0, priorityMode=18, HMAC=-75241946, scpUnitCount=0, header=[3, 18, 0, 0, -5, -125, -26, 38, -64, -88, 59, -27, -64, -88, 59, -27, 0, 0, 1, -124, -10, -18, 105, 44, 57, -34, 46, -89, -121, 64, 64, 111], pdu=true}, messageUnits=[], scpData=[3, 18, 0, 0, -5, -125, -26, 38, -64, -88, 59, -27, -64, -88, 59, -27, 0, 0, 1, -124, -10, -18, 105, 44, 57, -34, 46, -89, -121, 64, 64, 111, 80, 0, 0, 0, -94, 48, -127, -97, 48, 13, 6, 9, 42, -122, 72, -122, -9, 13, 1, 1, 1, 5, 0, 3, -127, -115, 0, 48, -127, -119, 2, -127, -127, 0, -85, -9, -71, -106, -118, -99, -30, 45, -68, -69, 45, 118, 32, -108, 93, -38, -128, 7, 41, -31, -89, 98, -75, 15, -18, -22, -35, -89, 28, -121, -82, 46, -21, 39, -55, -30, -57, 116, 21, 96, -74, 67, 82, 17, 100, -71, -115, -34, -9, -84, 100, -94, -42, 89, 85, -122, -100, 1, 85, -40, 127, 56, -103, -69, -56, -96, 71, -67, -4, -75, -31, 41, 7, 30, 44, -87, -8, -26, -119, 34, 26, -98, -116, -43, -12, 32, -59, -73, -75, -79, 13, 6, -48, -26, -16, 126, 50, 127, 18, -53, -101, -9, -99, 6, 53, 121, -67, -35, 49, -7, -110, -118, -118, -76, -39, 22, 18, -53, 72, -114, -121, -63, -83, 41, -29, -28, 110, 97, 2, 3, 1, 0, 1], payload=[80, 0, 0, 0, -94, 48, -127, -97, 48, 13, 6, 9, 42, -122, 72, -122, -9, 13, 1, 1, 1, 5, 0, 3, -127, -115, 0, 48, -127, -119, 2, -127, -127, 0, -85, -9, -71, -106, -118, -99, -30, 45, -68, -69, 45, 118, 32, -108, 93, -38, -128, 7, 41, -31, -89, 98, -75, 15, -18, -22, -35, -89, 28, -121, -82, 46, -21, 39, -55, -30, -57, 116, 21, 96, -74, 67, 82, 17, 100, -71, -115, -34, -9, -84, 100, -94, -42, 89, 85, -122, -100, 1, 85, -40, 127, 56, -103, -69, -56, -96, 71, -67, -4, -75, -31, 41, 7, 30, 44, -87, -8, -26, -119, 34, 26, -98, -116, -43, -12, 32, -59, -73, -75, -79, 13, 6, -48, -26, -16, 126, 50, 127, 18, -53, -101, -9, -99, 6, 53, 121, -67, -35, 49, -7, -110, -118, -118, -76, -39, 22, 18, -53, 72, -114, -121, -63, -83, 41, -29, -28, 110, 97, 2, 3, 1, 0, 1], pdu=ScpDataUnit{payload=[48, -127, -97, 48, 13, 6, 9, 42, -122, 72, -122, -9, 13, 1, 1, 1, 5, 0, 3, -127, -115, 0, 48, -127, -119, 2, -127, -127, 0, -85, -9, -71, -106, -118, -99, -30, 45, -68, -69, 45, 118, 32, -108, 93, -38, -128, 7, 41, -31, -89, 98, -75, 15, -18, -22, -35, -89, 28, -121, -82, 46, -21, 39, -55, -30, -57, 116, 21, 96, -74, 67, 82, 17, 100, -71, -115, -34, -9, -84, 100, -94, -42, 89, 85, -122, -100, 1, 85, -40, 127, 56, -103, -69, -56, -96, 71, -67, -4, -75, -31, 41, 7, 30, 44, -87, -8, -26, -119, 34, 26, -98, -116, -43, -12, 32, -59, -73, -75, -79, 13, 6, -48, -26, -16, 126, 50, 127, 18, -53, -101, -9, -99, 6, 53, 121, -67, -35, 49, -7, -110, -118, -118, -76, -39, 22, 18, -53, 72, -114, -121, -63, -83, 41, -29, -28, 110, 97, 2, 3, 1, 0, 1], pduType=80, payloadLength=162}}</message>
</record>
<record>
  <date>2022-12-09T18:18:50</date>
  <millis>1670590130478</millis>
  <sequence>20</sequence>
  <logger>scpLog</logger>
  <level>INFO</level>
  <class>com.sgs.sos.test.TestMain</class>
  <method>testHTTPWithPDU</method>
  <thread>15</thread>
  <message>PREP [80, 0, 0, 0, -94, 48, -127, -97, 48, 13, 6, 9, 42, -122, 72, -122, -9, 13, 1, 1, 1, 5, 0, 3, -127, -115, 0, 48, -127, -119, 2, -127, -127, 0, -85, -9, -71, -106, -118, -99, -30, 45, -68, -69, 45, 118, 32, -108, 93, -38, -128, 7, 41, -31, -89, 98, -75, 15, -18, -22, -35, -89, 28, -121, -82, 46, -21, 39, -55, -30, -57, 116, 21, 96, -74, 67, 82, 17, 100, -71, -115, -34, -9, -84, 100, -94, -42, 89, 85, -122, -100, 1, 85, -40, 127, 56, -103, -69, -56, -96, 71, -67, -4, -75, -31, 41, 7, 30, 44, -87, -8, -26, -119, 34, 26, -98, -116, -43, -12, 32, -59, -73, -75, -79, 13, 6, -48, -26, -16, 126, 50, 127, 18, -53, -101, -9, -99, 6, 53, 121, -67, -35, 49, -7, -110, -118, -118, -76, -39, 22, 18, -53, 72, -114, -121, -63, -83, 41, -29, -28, 110, 97, 2, 3, 1, 0, 1]</message>
</record>
<record>
  <date>2022-12-09T18:18:50</date>
  <millis>1670590130479</millis>
  <sequence>21</sequence>
  <logger>scpLog</logger>
  <level>INFO</level>
  <class>com.sgs.sos.io.ScpInputHandler</class>
  <method>handle</method>
  <thread>12</thread>
  <message>REQUEST_IN -&gt; address_in=192.168.59.229:8086</message>
</record>
<record>
  <date>2022-12-09T18:18:50</date>
  <millis>1670590130479</millis>
  <sequence>22</sequence>
  <logger>scpLog</logger>
  <level>INFO</level>
  <class>com.sgs.sos.io.ScpInputHandler</class>
  <method>handle</method>
  <thread>12</thread>
  <message>ScpData{header=ScpHeader{reserved=3, destAddress=[-64, -88, 59, -27], srcAddress=[-64, -88, 59, -27], payloadLength=0, timestamp=1670590130476, ssid=4169821602055209071, padding=0, priorityMode=18, HMAC=-75241946, scpUnitCount=0, header=[3, 18, 0, 0, -5, -125, -26, 38, -64, -88, 59, -27, -64, -88, 59, -27, 0, 0, 1, -124, -10, -18, 105, 44, 57, -34, 46, -89, -121, 64, 64, 111], pdu=true}, messageUnits=null, scpData=[3, 18, 0, 0, -5, -125, -26, 38, -64, -88, 59, -27, -64, -88, 59, -27, 0, 0, 1, -124, -10, -18, 105, 44, 57, -34, 46, -89, -121, 64, 64, 111, 80, 0, 0, 0, -94, 48, -127, -97, 48, 13, 6, 9, 42, -122, 72, -122, -9, 13, 1, 1, 1, 5, 0, 3, -127, -115, 0, 48, -127, -119, 2, -127, -127, 0, -85, -9, -71, -106, -118, -99, -30, 45, -68, -69, 45, 118, 32, -108, 93, -38, -128, 7, 41, -31, -89, 98, -75, 15, -18, -22, -35, -89, 28, -121, -82, 46, -21, 39, -55, -30, -57, 116, 21, 96, -74, 67, 82, 17, 100, -71, -115, -34, -9, -84, 100, -94, -42, 89, 85, -122, -100, 1, 85, -40, 127, 56, -103, -69, -56, -96, 71, -67, -4, -75, -31, 41, 7, 30, 44, -87, -8, -26, -119, 34, 26, -98, -116, -43, -12, 32, -59, -73, -75, -79, 13, 6, -48, -26, -16, 126, 50, 127, 18, -53, -101, -9, -99, 6, 53, 121, -67, -35, 49, -7, -110, -118, -118, -76, -39, 22, 18, -53, 72, -114, -121, -63, -83, 41, -29, -28, 110, 97, 2, 3, 1, 0, 1], payload=[80, 0, 0, 0, -94, 48, -127, -97, 48, 13, 6, 9, 42, -122, 72, -122, -9, 13, 1, 1, 1, 5, 0, 3, -127, -115, 0, 48, -127, -119, 2, -127, -127, 0, -85, -9, -71, -106, -118, -99, -30, 45, -68, -69, 45, 118, 32, -108, 93, -38, -128, 7, 41, -31, -89, 98, -75, 15, -18, -22, -35, -89, 28, -121, -82, 46, -21, 39, -55, -30, -57, 116, 21, 96, -74, 67, 82, 17, 100, -71, -115, -34, -9, -84, 100, -94, -42, 89, 85, -122, -100, 1, 85, -40, 127, 56, -103, -69, -56, -96, 71, -67, -4, -75, -31, 41, 7, 30, 44, -87, -8, -26, -119, 34, 26, -98, -116, -43, -12, 32, -59, -73, -75, -79, 13, 6, -48, -26, -16, 126, 50, 127, 18, -53, -101, -9, -99, 6, 53, 121, -67, -35, 49, -7, -110, -118, -118, -76, -39, 22, 18, -53, 72, -114, -121, -63, -83, 41, -29, -28, 110, 97, 2, 3, 1, 0, 1], pdu=ScpDataUnit{payload=[48, -127, -97, 48, 13, 6, 9, 42, -122, 72, -122, -9, 13, 1, 1, 1, 5, 0, 3, -127, -115, 0, 48, -127, -119, 2, -127, -127, 0, -85, -9, -71, -106, -118, -99, -30, 45, -68, -69, 45, 118, 32, -108, 93, -38, -128, 7, 41, -31, -89, 98, -75, 15, -18, -22, -35, -89, 28, -121, -82, 46, -21, 39, -55, -30, -57, 116, 21, 96, -74, 67, 82, 17, 100, -71, -115, -34, -9, -84, 100, -94, -42, 89, 85, -122, -100, 1, 85, -40, 127, 56, -103, -69, -56, -96, 71, -67, -4, -75, -31, 41, 7, 30, 44, -87, -8, -26, -119, 34, 26, -98, -116, -43, -12, 32, -59, -73, -75, -79, 13, 6, -48, -26, -16, 126, 50, 127, 18, -53, -101, -9, -99, 6, 53, 121, -67, -35, 49, -7, -110, -118, -118, -76, -39, 22, 18, -53, 72, -114, -121, -63, -83, 41, -29, -28, 110, 97, 2, 3, 1, 0, 1], pduType=80, payloadLength=162}}</message>
</record>
<record>
  <date>2022-12-09T18:18:50</date>
  <millis>1670590130481</millis>
  <sequence>23</sequence>
  <logger>scpLog</logger>
  <level>INFO</level>
  <class>com.sgs.sos.io.ScpProcessor</class>
  <method>process</method>
  <thread>12</thread>
  <message>Processing ScpData =&gt; ssid=4169821602055209071</message>
</record>
<record>
  <date>2022-12-09T18:18:50</date>
  <millis>1670590130481</millis>
  <sequence>24</sequence>
  <logger>scpLog</logger>
  <level>INFO</level>
  <class>com.sgs.sos.server.ScpSocketHandler$DownstreamResponder</class>
  <method>sendResponse</method>
  <thread>15</thread>
  <message>DATA_OUT -&gt; destination=192.168.59.229:8085</message>
</record>
</log>
